valiant_valiant_inequality_prover/__init__.py
valiant_valiant_inequality_prover/prover.py
valiant_valiant_inequality_prover-1.0.3.dist-info/LICENSE
valiant_valiant_inequality_prover-1.0.3.dist-info/METADATA
valiant_valiant_inequality_prover-1.0.3.dist-info/WHEEL
valiant_valiant_inequality_prover-1.0.3.dist-info/top_level.txt
valiant_valiant_inequality_prover-1.0.3.dist-info/RECORD
